{
"type": "FeatureCollection",
"name": "Category_7",
"crs": { "type": "name", "properties": { "name": "urn:ogc:def:crs:OGC:1.3:CRS84" } },
"features": [
{ "type": "Feature", "properties": { "Name_CH": "巴生中华独立中学", "Name_ML": null, "Name_EN": "Chung Hua Independent High School", "Location": "129, Jalan Kota Raya, 41000 Klang, Selangor.", "Region": "Selangor", "Category": "独立中学", "PageNumber": 414, "Country": "Malaysia", "latitude": 3.0366218, "longitude": 101.4527413 }, "geometry": { "type": "Point", "coordinates": [ 101.4527413, 3.0366218 ] } },
{ "type": "Feature", "properties": { "Name_CH": "巴生中华独立中学", "Name_ML": null, "Name_EN": "Chung Hua Independent High School", "Location": "129, Jalan Kota Raya, 41000 Klang, Selangor.", "Region": "Selangor", "Category": "独立中学", "PageNumber": 414, "Country": "Malaysia", "latitude": 3.0366218, "longitude": 101.4527413 }, "geometry": { "type": "Point", "coordinates": [ 101.4527413, 3.0366218 ] } },
{ "type": "Feature", "properties": { "Name_CH": "巴生滨华中学", "Name_ML": null, "Name_EN": "Pin Hwa High School", "Location": "13, Jalan Goh Hock Huat, 41400 Kiang, Selangor.", "Region": "Selangor", "Category": "独立中学", "PageNumber": 414, "Country": "Malaysia", "latitude": 3.0515148, "longitude": 101.4464635 }, "geometry": { "type": "Point", "coordinates": [ 101.4464635, 3.0515148 ] } },
{ "type": "Feature", "properties": { "Name_CH": "巴生滨华中学", "Name_ML": null, "Name_EN": "Pin Hwa High School", "Location": "13, Jalan Goh Hock Huat, 41400 Kiang, Selangor.", "Region": "Selangor", "Category": "独立中学", "PageNumber": 414, "Country": "Malaysia", "latitude": 3.0515148, "longitude": 101.4464635 }, "geometry": { "type": "Point", "coordinates": [ 101.4464635, 3.0515148 ] } },
{ "type": "Feature", "properties": { "Name_CH": "巴生兴华中学", "Name_ML": null, "Name_EN": null, "Location": "141, Persiaran Raja Muda Musa, 41200 Klang, Selangor.", "Region": "Selangor", "Category": "独立中学", "PageNumber": 415, "Country": "Malaysia", "latitude": 3.0265621, "longitude": 101.4251254 }, "geometry": { "type": "Point", "coordinates": [ 101.4251254, 3.0265621 ] } },
{ "type": "Feature", "properties": { "Name_CH": "巴生兴华中学", "Name_ML": null, "Name_EN": null, "Location": "141, Persiaran Raja Muda Musa, 41200 Klang, Selangor.", "Region": "Selangor", "Category": "独立中学", "PageNumber": 415, "Country": "Malaysia", "latitude": 3.0265621, "longitude": 101.4251254 }, "geometry": { "type": "Point", "coordinates": [ 101.4251254, 3.0265621 ] } },
{ "type": "Feature", "properties": { "Name_CH": "巴生光华中学", "Name_ML": null, "Name_EN": "Kwang Hua (Private) High School", "Location": "1, jalan 17, Kawasan 17, Taman Eng Ann, 41150 Klang, Selangor.", "Region": "Selangor", "Category": "独立中学", "PageNumber": 415, "Country": "Malaysia", "latitude": 3.0615192, "longitude": 101.4605886 }, "geometry": { "type": "Point", "coordinates": [ 101.4605886, 3.0615192 ] } },
{ "type": "Feature", "properties": { "Name_CH": "巴生光华中学", "Name_ML": null, "Name_EN": "Kwang Hua (Private) High School", "Location": "1, jalan 17, Kawasan 17, Taman Eng Ann, 41150 Klang, Selangor.", "Region": "Selangor", "Category": "独立中学", "PageNumber": 415, "Country": "Malaysia", "latitude": 3.0615192, "longitude": 101.4605886 }, "geometry": { "type": "Point", "coordinates": [ 101.4605886, 3.0615192 ] } }
]
}
