{
"type": "FeatureCollection",
"name": "Category_2",
"crs": { "type": "name", "properties": { "name": "urn:ogc:def:crs:OGC:1.3:CRS84" } },
"features": [
{ "type": "Feature", "properties": { "Name_CH": "芙蓉中华中学", "Name_ML": null, "Name_EN": "Chung Hua High School", "Location": "PO BOX 154, Jalan Tun Dr. Ismail, 70710 Seremban, Negeri Sembilan.", "Longitude": 101.935051, "Latitude": 2.73366, "Region": "Negeri Sembilan", "Category": "独立中学", "PageNumber": "415" }, "geometry": { "type": "Point", "coordinates": [ 101.9351, 2.7337, 101.9351 ] } },
{ "type": "Feature", "properties": { "Name_CH": "波德申中华中学", "Name_ML": null, "Name_EN": "Chung Hua Middle School", "Location": "PO BOX 29, 71007 Port Dickson, Negeri Sembilan.", "Longitude": 102.611212, "Latitude": 2.58121, "Region": "Negeri Sembilan", "Category": "独立中学", "PageNumber": "415" }, "geometry": { "type": "Point", "coordinates": [ 102.6112, 2.5812, 102.6112 ] } }
]
}
