{"type": "FeatureCollection", "name": "region_12", "crs": {"type": "name", "properties": {"name": "urn:ogc:def:crs:OGC:1.3:CRS84"}}, "features": [{"type": "Feature", "properties": {"Name_CH": "\u9a6c\u516d\u7532\u57f9\u98ce\u4e2d\u5b66", "Name_ML": null, "Name_EN": "Pay Fong High School", "Location": "40, Jalan Tan Chay Yon, 75300, Melaka.", "Region": "Melaka", "Category": "\u72ec\u7acb\u4e2d\u5b66", "PageNumber": 415, "Country": "Malaysia", "latitude": 2.201417, "longitude": 102.2439867}, "geometry": {"type": "Point", "coordinates": [102.2439867, 2.201417]}}]}